heaserver/service/__init__.py
heaserver/service/activity.py
heaserver/service/aiohttp.py
heaserver/service/appfactory.py
heaserver/service/appproperty.py
heaserver/service/backgroundtasks.py
heaserver/service/caching.py
heaserver/service/caching_strategy.py
heaserver/service/client.py
heaserver/service/config.py
heaserver/service/crypt.py
heaserver/service/customhdrs.py
heaserver/service/defaults.py
heaserver/service/emailutil.py
heaserver/service/error.py
heaserver/service/expression.py
heaserver/service/functional.py
heaserver/service/heaobjectsupport.py
heaserver/service/jsonschema.py
heaserver/service/jsonschemavalidator.py
heaserver/service/logging.py
heaserver/service/messagebroker.py
heaserver/service/mimetypes.py
heaserver/service/oidcclaimhdrs.py
heaserver/service/openapi.py
heaserver/service/py.typed
heaserver/service/registryproperty.py
heaserver/service/requestproperty.py
heaserver/service/response.py
heaserver/service/runner.py
heaserver/service/sources.py
heaserver/service/uritemplate.py
heaserver/service/util.py
heaserver/service/wstl.py
heaserver/service/db/__init__.py
heaserver/service/db/aws.py
heaserver/service/db/awsaction.py
heaserver/service/db/awsservicelib.py
heaserver/service/db/database.py
heaserver/service/db/dbapi2.py
heaserver/service/db/mongo.py
heaserver/service/db/mongoexpr.py
heaserver/service/db/mongoservicelib.py
heaserver/service/db/opensearch.py
heaserver/service/db/opensearchlib.py
heaserver/service/jsonschemafiles/__init__.py
heaserver/service/jsonschemafiles/cjtemplate.json
heaserver/service/jsonschemafiles/nvpjson.json
heaserver/service/jsonschemafiles/wstl.json
heaserver/service/jsonschemafiles/wstlaction.json
heaserver/service/representor/__init__.py
heaserver/service/representor/cj.py
heaserver/service/representor/error.py
heaserver/service/representor/factory.py
heaserver/service/representor/nvpjson.py
heaserver/service/representor/representor.py
heaserver/service/representor/wstljson.py
heaserver-1.52.0.dist-info/licenses/LICENSE
heaserver-1.52.0.dist-info/METADATA
heaserver-1.52.0.dist-info/WHEEL
heaserver-1.52.0.dist-info/top_level.txt
heaserver-1.52.0.dist-info/RECORD
