Metadata-Version: 2.4
Name: heaserver
Version: 1.52.0
Summary: The server side of HEA.
Home-page: https://risr.hci.utah.edu
Author: Research Informatics Shared Resource, Huntsman Cancer Institute, Salt Lake City, UT
Author-email: Andrew.Post@hci.utah.edu
License: Apache License 2.0
Classifier: Development Status :: 5 - Production/Stable
Classifier: Environment :: Console
Classifier: Intended Audience :: Developers
Classifier: Natural Language :: English
Classifier: Operating System :: OS Independent
Classifier: Programming Language :: Python
Classifier: Programming Language :: Python :: 3
Classifier: Programming Language :: Python :: 3.10
Classifier: Programming Language :: Python :: 3.11
Classifier: Programming Language :: Python :: 3.12
Classifier: Programming Language :: Python :: Implementation :: CPython
Classifier: Topic :: Software Development
Classifier: Topic :: Scientific/Engineering
Classifier: Topic :: Scientific/Engineering :: Bio-Informatics
Classifier: Topic :: Scientific/Engineering :: Information Analysis
Classifier: Topic :: Scientific/Engineering :: Medical Science Apps.
Requires-Python: >=3.10
License-File: LICENSE
Requires-Dist: typing_extensions>=4.0.0; python_version < "3.11"
Requires-Dist: heaobject~=1.36.0
Requires-Dist: aiohttp~=3.10.10
Requires-Dist: aiodns; platform_system != "Windows"
Requires-Dist: pycares<5.0.0,>=4.9.0; platform_system != "Windows"
Requires-Dist: Brotli
Requires-Dist: aiohttp-remotes~=1.3.0
Requires-Dist: motor~=3.6.0
Requires-Dist: motor-types~=1.0.0b4
Requires-Dist: accept-types~=0.4.1
Requires-Dist: mongoquery~=1.4.2
Requires-Dist: jsonschema~=4.23.0
Requires-Dist: jsonmerge~=1.9.2
Requires-Dist: requests~=2.31.0
Requires-Dist: types-requests>=2.32.0.20241016
Requires-Dist: boto3[crt]~=1.37.25
Requires-Dist: botocore~=1.37.25
Requires-Dist: boto3-stubs[account,essential,iam,organizations,sts]~=1.37.25
Requires-Dist: botocore-stubs[essential]~=1.37.25
Requires-Dist: freezegun~=1.5.1
Requires-Dist: regex~=2024.11.6
Requires-Dist: aio-pika==9.5.1
Requires-Dist: simpleeval~=1.0.3
Requires-Dist: opensearch-py[async]~=2.6.0
Requires-Dist: cachetools~=5.5.0
Requires-Dist: types-cachetools~=5.5.0.20240820
Requires-Dist: types-pywin32; platform_system == "Windows"
Requires-Dist: uvloop~=0.21.0; platform_system != "Windows"
Requires-Dist: aiodiskqueue~=0.1.2
Requires-Dist: aiosqlite~=0.21.0
Dynamic: author
Dynamic: author-email
Dynamic: classifier
Dynamic: description
Dynamic: description-content-type
Dynamic: home-page
Dynamic: license
Dynamic: license-file
Dynamic: requires-dist
Dynamic: requires-python
Dynamic: summary
